simple_pushover.py
simple_pushover-0.0.5.dist-info/LICENSE
simple_pushover-0.0.5.dist-info/METADATA
simple_pushover-0.0.5.dist-info/WHEEL
simple_pushover-0.0.5.dist-info/top_level.txt
simple_pushover-0.0.5.dist-info/RECORD
