Metadata-Version: 2.1
Name: simple-pushover
Version: 0.0.5
Summary: A simple and easy to use package to help send push notifications via pushover.net.
Author-email: Christopher Hedrick <cmhedrick@protonmail.com>
Project-URL: Homepage, https://gitlab.com/cmhedrick/pushover/-/tree/main
Project-URL: Bug Tracker, https://gitlab.com/cmhedrick/pushover/-/issues
Classifier: Programming Language :: Python :: 3
Classifier: License :: OSI Approved :: GNU General Public License v3 (GPLv3)
Classifier: Operating System :: OS Independent
Requires-Python: >=3.9
License-File: LICENSE
